patann/__init__.py
patann/cli.py
patann/version.py
patann/clib/linux/x86_64/libpatann.so
patann/clib/linux/x86_64/libpatann.sum
patann/clib/linux/x86_64/3.10/_patann.so
patann/clib/linux/x86_64/3.10/_patann.sum
patann/clib/linux/x86_64/3.11/_patann.so
patann/clib/linux/x86_64/3.11/_patann.sum
patann/clib/linux/x86_64/3.12/_patann.so
patann/clib/linux/x86_64/3.12/_patann.sum
patann/clib/linux/x86_64/3.13/_patann.so
patann/clib/linux/x86_64/3.13/_patann.sum
patann/clib/linux/x86_64/3.9/_patann.so
patann/clib/linux/x86_64/3.9/_patann.sum
patann/clib/macos/arm64/libpatann.so
patann/clib/macos/arm64/libpatann.sum
patann/clib/macos/arm64/3.10/_patann.so
patann/clib/macos/arm64/3.10/_patann.sum
patann/clib/macos/arm64/3.11/_patann.so
patann/clib/macos/arm64/3.11/_patann.sum
patann/clib/macos/arm64/3.12/_patann.so
patann/clib/macos/arm64/3.12/_patann.sum
patann/clib/macos/arm64/3.13/_patann.so
patann/clib/macos/arm64/3.13/_patann.sum
patann/clib/macos/arm64/3.9/_patann.so
patann/clib/macos/arm64/3.9/_patann.sum
patann/clib/windows/x86_64/patann.dll
patann/clib/windows/x86_64/patann.sum
patann/clib/windows/x86_64/3.10/_patann.pyd
patann/clib/windows/x86_64/3.10/_patann.sum
patann/clib/windows/x86_64/3.11/_patann.pyd
patann/clib/windows/x86_64/3.11/_patann.sum
patann/clib/windows/x86_64/3.12/_patann.pyd
patann/clib/windows/x86_64/3.12/_patann.sum
patann/clib/windows/x86_64/3.13/_patann.pyd
patann/clib/windows/x86_64/3.13/_patann.sum
patann/clib/windows/x86_64/3.9/_patann.dll
patann/clib/windows/x86_64/3.9/_patann.pyd
patann/clib/windows/x86_64/3.9/_patann.sum
patann/examples/patann_async_example.py
patann/examples/patann_async_parallel_example.py
patann/examples/patann_sync_example.py
patann/examples/patann_utils.py
patann-0.1.3.dist-info/METADATA
patann-0.1.3.dist-info/WHEEL
patann-0.1.3.dist-info/entry_points.txt
patann-0.1.3.dist-info/top_level.txt
patann-0.1.3.dist-info/RECORD
