Metadata-Version: 2.4
Name: patann
Version: 0.1.3
Summary: PatANN is a massively parallel, distributed, and scalable in-memory/on-disk vector database library for efficient nearest neighbor search across large-scale datasets by finding vector patterns.
Home-page: https://github.com/mesibo/patann
Author: https://patann.dev
Author-email: support@mesibo.com
License: Beta - See LICENSE.txt
Project-URL: Bug Tracker, https://github.com/mesibo/patann/issues
Keywords: vector database,similarity search,ANN,nearest neighbor,AI,embeddings,vector search
Classifier: Development Status :: 4 - Beta
Classifier: Intended Audience :: Developers
Classifier: Operating System :: POSIX :: Linux
Classifier: Operating System :: POSIX :: BSD
Classifier: Operating System :: Unix
Classifier: Operating System :: MacOS
Classifier: Operating System :: Microsoft :: Windows
Classifier: Programming Language :: Python
Classifier: Programming Language :: Python :: 3
Classifier: Topic :: Software Development :: Libraries :: Python Modules
Classifier: Topic :: Scientific/Engineering :: Artificial Intelligence
Classifier: Topic :: Database
Requires-Python: >=3.9
Requires-Dist: numpy>=1.19.0
Dynamic: author
Dynamic: author-email
Dynamic: classifier
Dynamic: description
Dynamic: description-content-type
Dynamic: home-page
Dynamic: keywords
Dynamic: license
Dynamic: project-url
Dynamic: requires-dist
Dynamic: requires-python
Dynamic: summary
